modstablib/__init__.py
modstablib/metrics/__init__.py
modstablib/metrics/_performance.py
modstablib-0.1.2.dist-info/licenses/LICENSE
modstablib-0.1.2.dist-info/METADATA
modstablib-0.1.2.dist-info/WHEEL
modstablib-0.1.2.dist-info/top_level.txt
modstablib-0.1.2.dist-info/RECORD
